locktools/__init__.py
locktools/locktools.py
locktools-0.3.2.dist-info/licenses/LICENSE
locktools-0.3.2.dist-info/METADATA
locktools-0.3.2.dist-info/WHEEL
locktools-0.3.2.dist-info/top_level.txt
locktools-0.3.2.dist-info/RECORD
