Metadata-Version: 2.4
Name: locktools
Version: 0.3.2
Summary: A simple file-based lock utility for Python applications
Author-email: Rodrigo Licks <rodrigo.licks@uol.com.br>
License: MIT License
Keywords: lock,file,synchronization,python
Classifier: Programming Language :: Python :: 3
Classifier: License :: OSI Approved :: MIT License
Classifier: Operating System :: OS Independent
Classifier: Development Status :: 4 - Beta
Classifier: Intended Audience :: Developers
Classifier: Topic :: Software Development :: Libraries :: Python Modules
Requires-Python: >=3.5
License-File: LICENSE
Dynamic: license-file
